knowledge_mapper/__init__.py
knowledge_mapper/__main__.py
knowledge_mapper/data_source.py
knowledge_mapper/knowledge_base.py
knowledge_mapper/knowledge_interaction.py
knowledge_mapper/knowledge_mapper.py
knowledge_mapper/sparql_source.py
knowledge_mapper/sql_source.py
knowledge_mapper/tke_client.py
knowledge_mapper/tke_exceptions.py
knowledge_mapper/utils.py
knowledge_mapper/wizard_mapper.py
knowledge_mapper/auth/__init__.py
knowledge_mapper/auth/base_auth.py
knowledge_mapper/auth/sql_auth.py
knowledge_mapper/auth/static_auth.py
knowledge_mapper/tests/__init__.py
knowledge_mapper/tests/test_extract_variables.py
knowledge_mapper/tests/test_match_bindings.py
knowledge_mapper/tests/test_tke_client.py
knowledge_mapper-0.0.24.dist-info/METADATA
knowledge_mapper-0.0.24.dist-info/WHEEL
knowledge_mapper-0.0.24.dist-info/entry_points.txt
knowledge_mapper-0.0.24.dist-info/top_level.txt
knowledge_mapper-0.0.24.dist-info/RECORD
