Metadata-Version: 2.1
Name: knowledge-mapper
Version: 0.0.24
Requires-Dist: requests
Requires-Dist: mysql-connector-python
Requires-Dist: json5
Requires-Dist: websockets
Requires-Dist: rdflib
